django_email_foundation/__init__.py
django_email_foundation/api.py
django_email_foundation/gulpfile.js
django_email_foundation/settings.py
django_email_foundation/urls.py
django_email_foundation/utils.py
django_email_foundation/views.py
django_email_foundation/__pycache__/__init__.cpython-36.pyc
django_email_foundation/__pycache__/__init__.cpython-37.pyc
django_email_foundation/__pycache__/api.cpython-36.pyc
django_email_foundation/__pycache__/api.cpython-37.pyc
django_email_foundation/__pycache__/settings.cpython-36.pyc
django_email_foundation/__pycache__/settings.cpython-37.pyc
django_email_foundation/__pycache__/urls.cpython-36.pyc
django_email_foundation/__pycache__/urls.cpython-37.pyc
django_email_foundation/__pycache__/utils.cpython-36.pyc
django_email_foundation/__pycache__/utils.cpython-37.pyc
django_email_foundation/__pycache__/views.cpython-36.pyc
django_email_foundation/__pycache__/views.cpython-37.pyc
django_email_foundation/default_templates/assets/scss/_settings.scss
django_email_foundation/default_templates/assets/scss/app.scss
django_email_foundation/default_templates/assets/scss/template/_template.scss
django_email_foundation/default_templates/data/__init__.py
django_email_foundation/default_templates/data/context.py
django_email_foundation/default_templates/data/__pycache__/__init__.cpython-36.pyc
django_email_foundation/default_templates/layouts/default.html
django_email_foundation/management/__init__.py
django_email_foundation/management/__pycache__/__init__.cpython-36.pyc
django_email_foundation/management/commands/__init__.py
django_email_foundation/management/commands/create_basic_structure.py
django_email_foundation/management/commands/email_builder.py
django_email_foundation/management/commands/install_requires.py
django_email_foundation/management/commands/__pycache__/__init__.cpython-36.pyc
django_email_foundation/management/commands/__pycache__/create_basic_structure.cpython-36.pyc
django_email_foundation-0.0.11.dist-info/LICENSE
django_email_foundation-0.0.11.dist-info/METADATA
django_email_foundation-0.0.11.dist-info/WHEEL
django_email_foundation-0.0.11.dist-info/top_level.txt
django_email_foundation-0.0.11.dist-info/RECORD
