Metadata-Version: 2.1
Name: django-email-foundation
Version: 0.0.11
Summary: django-email-foundation is a Django package for help you to create emails using the "zurb foundation" technologies
Home-page: http://github.com/APSL/django-email-foundation
Author: Francesc Arpí
Author-email: francesc.arpi@gmail.com
License: UNKNOWN
Platform: UNKNOWN
Classifier: Development Status :: 5 - Production/Stable
Classifier: Environment :: Web Environment
Classifier: Intended Audience :: Developers
Classifier: License :: OSI Approved :: Apache Software License
Classifier: Operating System :: OS Independent
Classifier: Programming Language :: Python
Classifier: Programming Language :: Python :: 3.6
Classifier: Framework :: Django
Classifier: Framework :: Django :: 2.1
